llmwalk/__init__.py
llmwalk/__main__.py
llmwalk/cli.py
llmwalk/llm.py
llmwalk-0.2.0.dist-info/METADATA
llmwalk-0.2.0.dist-info/WHEEL
llmwalk-0.2.0.dist-info/entry_points.txt
llmwalk-0.2.0.dist-info/licenses/LICENSE
llmwalk-0.2.0.dist-info/RECORD
