Metadata-Version: 2.4
Name: llmwalk
Version: 0.2.0
Summary: Explore the answer-space for any prompt and any MLX-supported model.
License-File: LICENSE
Requires-Python: >=3.10
Requires-Dist: mlx-lm==0.29.1
Requires-Dist: rich==14.2.0
Requires-Dist: sortedcontainers==2.4.0
Requires-Dist: transformers===4.57.3
Provides-Extra: dev
Requires-Dist: pytest>=8.0.0; extra == 'dev'
Requires-Dist: syrupy>=4.0.0; extra == 'dev'
